ftrack_ams/__init__.py
ftrack_ams/add.py
ftrack_ams/console.py
ftrack_ams/fileserver.py
ftrack_ams/functions.py
ftrack_ams/main.py
ftrack_ams/test.py
ftrack_ams/ui.py
ftrack_ams-2.0.30.dist-info/entry_points.txt
ftrack_ams-2.0.30.dist-info/LICENSE
ftrack_ams-2.0.30.dist-info/WHEEL
ftrack_ams-2.0.30.dist-info/METADATA
ftrack_ams-2.0.30.dist-info/RECORD
