Metadata-Version: 2.1
Name: ftrack-ams
Version: 2.0.30
Summary: 
Author: Lucas Selfslagh
Author-email: lucas@animotions.be
Requires-Python: >=3.8
Classifier: Programming Language :: Python :: 3
Classifier: Programming Language :: Python :: 3.8
Classifier: Programming Language :: Python :: 3.9
Classifier: Programming Language :: Python :: 3.10
Requires-Dist: PyQt5 (>=5.15.9,<6.0.0)
Requires-Dist: click (>=8.0.3,<9.0.0)
Requires-Dist: ftrack-python-api (>=2.3.1,<3.0.0)
Requires-Dist: pick (>=1.2.0,<2.0.0)
